{"members": [{"repository": "git://git.code.sf.net/p/fitlibrary/fitlibrary", "methodNumberBeforeChange": 23, "signatureBeforeChange": "\r \tvoid exceptionMayBeExpected(boolean exceptionExpected, Exception e,\r \t\t\tTestResults testResults);", "fileName": "src/fitlibrary/table/Cell.java", "methodNumberAfterChange": 22, "commitBeforeChange": "681d5f08a03cb8efaa429831112a5d45fa950ef3", "diff": ["-\tvoid exceptionMayBeExpected(boolean exceptionExpected, Exception e,\r", "+\tvoid exceptionExpected(boolean exceptionExpected, Exception e, TestResults testResults);\r"], "commitAfterChange": "e2da601cf629ddf34f7877021df06bd4f5925d28", "signatureAfterChange": "\r \tvoid exceptionExpected(boolean exceptionExpected, Exception e, TestResults testResults);", "id": "2352c1b67f5d242a909f519a2a2d7ce9", "@class": "de.fau.cs.inf2.cthree.data.CodeChange"}, {"repository": "git://git.code.sf.net/p/fitlibrary/fitlibrary", "methodNumberBeforeChange": 31, "signatureBeforeChange": "\r     public void exceptionMayBeExpected(boolean exceptionExpected, Exception e, TestResults testResults)", "fileName": "src/fitlibrary/table/CellOnParse.java", "methodNumberAfterChange": 30, "commitBeforeChange": "681d5f08a03cb8efaa429831112a5d45fa950ef3", "diff": ["-    public void exceptionMayBeExpected(boolean exceptionExpected, Exception e, TestResults testResults) {\r", "+    public void exceptionExpected(boolean exceptionExpected, Exception e, TestResults testResults) {\r"], "commitAfterChange": "e2da601cf629ddf34f7877021df06bd4f5925d28", "signatureAfterChange": "\r     public void exceptionExpected(boolean exceptionExpected, Exception e, TestResults testResults)", "id": "5b224c47a53a5f69c73e3a664622fe4d", "@class": "de.fau.cs.inf2.cthree.data.CodeChange"}], "id": "fc5ac80131438e1070feb8c2e580e018", "@class": "de.fau.cs.inf2.cthree.data.Cluster", "detectedBy": ["DIFF_DBSCAN"]}