{"@class": "de.fau.cs.inf2.cthree.data.Cluster", "id": "5df9d89420b44f34cbc22153c44cf3c9", "detectedBy": ["DIFF_DBSCAN"], "members": [{"@class": "de.fau.cs.inf2.cthree.data.CodeChange", "id": "69aadd29ad3abaf1eb0ba562074e201b", "repository": "https://git-wip-us.apache.org/repos/asf/ant.git", "fileName": "src/main/org/apache/tools/ant/taskdefs/Javac.java", "commitBeforeChange": "996bcb97e1d9fbf54a97b263f6cf33c005ae540d", "commitAfterChange": "b1c63b2dee167ba4ecc1d135a4175e0b831ebbcd", "methodNumberBeforeChange": 1, "methodNumberAfterChange": 1, "signatureBeforeChange": "      private String assumedJavaVersion()", "signatureAfterChange": "      private String assumedJavaVersion()", "diff": ["+        } else if (JavaEnvUtils.isJavaVersion(JavaEnvUtils.JAVA_1_6)) {", "+            return JAVAC16;"]}, {"@class": "de.fau.cs.inf2.cthree.data.CodeChange", "id": "a2b9c3ebc40541ece28ca163a069e7e0", "repository": "https://git-wip-us.apache.org/repos/asf/ant.git", "fileName": "src/main/org/apache/tools/ant/taskdefs/optional/javah/JavahAdapterFactory.java", "commitBeforeChange": "651ed09ed12be964dcff7c3b2001fdfa4380ab29", "commitAfterChange": "7f25ba893fa79265e4011a5e3c6e3b39567ca084", "methodNumberBeforeChange": 0, "methodNumberAfterChange": 0, "signatureBeforeChange": "     public static String getDefault()", "signatureAfterChange": "     public static String getDefault()", "diff": ["+        } else if (JavaEnvUtils.isGij()) {", "+            return Gcjh.IMPLEMENTATION_NAME;"]}, {"@class": "de.fau.cs.inf2.cthree.data.CodeChange", "id": "a62330008882f55a1e6274e3abb2590d", "repository": "https://git-wip-us.apache.org/repos/asf/ant.git", "fileName": "src/main/org/apache/tools/ant/taskdefs/Javac.java", "commitBeforeChange": "43430b54130b76767f98236e0681ba9a8582d35f", "commitAfterChange": "132fb32522052091d672208e63b418926e297bb2", "methodNumberBeforeChange": 1, "methodNumberAfterChange": 1, "signatureBeforeChange": "      private String assumedJavaVersion()", "signatureAfterChange": "      private String assumedJavaVersion()", "diff": ["+        } else if (JavaEnvUtils.isJavaVersion(JavaEnvUtils.JAVA_1_8)) {", "+            return JAVAC18;"]}, {"@class": "de.fau.cs.inf2.cthree.data.CodeChange", "id": "ad7e8e6a2645aa229048895b28fa2c10", "repository": "https://git-wip-us.apache.org/repos/asf/ant.git", "fileName": "src/main/org/apache/tools/ant/taskdefs/Javac.java", "commitBeforeChange": "9016f410697a0d613609a17549fdb69a482caaab", "commitAfterChange": "40e298139fafbe0b8a5694c0175d6e43b254acf8", "methodNumberBeforeChange": 1, "methodNumberAfterChange": 1, "signatureBeforeChange": "      private String assumedJavaVersion()", "signatureAfterChange": "      private String assumedJavaVersion()", "diff": ["+        } else if (JavaEnvUtils.isJavaVersion(JavaEnvUtils.JAVA_1_7)) {", "+            return JAVAC17;"]}, {"@class": "de.fau.cs.inf2.cthree.data.CodeChange", "id": "b18925018a47a389a5b1731be52e958e", "repository": "https://git-wip-us.apache.org/repos/asf/ant.git", "fileName": "src/main/org/apache/tools/ant/taskdefs/Javac.java", "commitBeforeChange": "241a7d6d0ce4f4235f1684cd0f1d6081c43076b2", "commitAfterChange": "4c0b73f72630fa7b07bc92dcf4855327265911f1", "methodNumberBeforeChange": 1, "methodNumberAfterChange": 1, "signatureBeforeChange": "      private String assumedJavaVersion()", "signatureAfterChange": "      private String assumedJavaVersion()", "diff": ["+        } else if (JavaEnvUtils.isJavaVersion(JavaEnvUtils.JAVA_1_9)) {", "+            return JAVAC19;"]}]}